vcams/__init__.py
vcams/bc.py
vcams/helper.py
vcams/logger_conf.py
vcams/output.py
vcams/voxelpart.py
vcams/mask/__init__.py
vcams/mask/function.py
vcams/mask/image.py
vcams/mask/random.py
vcams/mask/shape.py
vcams/mask/shape_dispersion.py
vcams/mask/tpms.py
vcams-3.1.2.dist-info/licenses/LICENSE
vcams-3.1.2.dist-info/METADATA
vcams-3.1.2.dist-info/WHEEL
vcams-3.1.2.dist-info/top_level.txt
vcams-3.1.2.dist-info/RECORD
