Metadata-Version: 2.4
Name: vcams
Version: 3.1.2
Summary: A Program and Python Library for Voxel-Based Computer-Aided Modeling of Complex Structures
License:                     GNU AFFERO GENERAL PUBLIC LICENSE
Project-URL: Homepage, https://vcams.mkhoshbin.com/
Project-URL: Documentation, https://vcams.readthedocs.io
Project-URL: Issues, https://github.com/mkhoshbin1/vcams/issues
Project-URL: Source Code, https://github.com/mkhoshbin1/vcams
Project-URL: Author's Website, https://www.mkhoshbin.com/
Keywords: abaqus,cae,fea,fem,finite-elements,finite-element-analysis,finite-element-method,finite-element-mesh,mesh-processing,voxel,gui,mechanical-engineering,scientific-research
Classifier: Development Status :: 5 - Production/Stable
Classifier: Intended Audience :: Developers
Classifier: Intended Audience :: Education
Classifier: Intended Audience :: Manufacturing
Classifier: Intended Audience :: Science/Research
Classifier: Topic :: Scientific/Engineering
Classifier: License :: OSI Approved :: GNU Affero General Public License v3 or later (AGPLv3+)
Classifier: Programming Language :: Python :: 3.12
Classifier: Operating System :: Microsoft :: Windows
Requires-Python: >=3.12
License-File: LICENSE
Requires-Dist: numpy>=2.1.0
Requires-Dist: scipy>=1.14.0
Requires-Dist: scikit-image>=0.24.0
Requires-Dist: matplotlib>=3.9.2
Requires-Dist: tabulate2>=1.9.0
Requires-Dist: PyQt5>=5.15.10
Provides-Extra: dev
Requires-Dist: pyinstaller-versionfile>=2.1.1; extra == "dev"
Requires-Dist: PyInstaller; extra == "dev"
Requires-Dist: build; extra == "dev"
Requires-Dist: sphinx; extra == "dev"
Requires-Dist: sphinx-rtd-theme; extra == "dev"
Requires-Dist: sphinx-autodoc-typehints; extra == "dev"
Dynamic: license-file
